mattstools/__init__.py
mattstools/distances.py
mattstools/lookahead.py
mattstools/loss.py
mattstools/modules.py
mattstools/network.py
mattstools/plotting.py
mattstools/schedulers.py
mattstools/torch_utils.py
mattstools/trainer.py
mattstools/transformers.py
mattstools/utils.py
mattstools-0.0.1.dist-info/LICENSE
mattstools-0.0.1.dist-info/METADATA
mattstools-0.0.1.dist-info/WHEEL
mattstools-0.0.1.dist-info/top_level.txt
mattstools-0.0.1.dist-info/RECORD
